indico_plugin_unipievents-0.3.3.dist-info/licenses/LICENSE
indico_unipievents/__init__.py
indico_unipievents/controllers.py
indico_unipievents/forms.py
indico_unipievents/plugin.py
indico_unipievents/views.py
indico_unipievents/wordpress.py
indico_unipievents/static/main.js
indico_unipievents/templates/sync.html
indico_plugin_unipievents-0.3.3.dist-info/METADATA
indico_plugin_unipievents-0.3.3.dist-info/WHEEL
indico_plugin_unipievents-0.3.3.dist-info/entry_points.txt
indico_plugin_unipievents-0.3.3.dist-info/top_level.txt
indico_plugin_unipievents-0.3.3.dist-info/RECORD
