Metadata-Version: 2.4
Name: indico_plugin_unipievents
Version: 0.3.3
Summary: UnipiEvents integration for Indico
Home-page: https://github.com/robol/indico-plugin-unipievents
Author: Leonardo Robol
Author-email: leonardo.robol@unipi.it
License: MIT
Classifier: Environment :: Plugins
Classifier: Environment :: Web Environment
Classifier: License :: OSI Approved :: MIT License
Classifier: Programming Language :: Python :: 3.9
Classifier: Programming Language :: Python :: 3.10
Classifier: Programming Language :: Python :: 3.11
Classifier: Programming Language :: Python :: 3.12
Requires-Python: >=3.9
License-File: LICENSE
Requires-Dist: indico>=3.1
Dynamic: license-file
